<?xml version="1.0" encoding="utf-8"?>
<data>
  <DataType Name="" BaseType="" ArrayType="" Length="" InitialValue="" EnumValue="" Comment="" OffsetChannel="" OffsetBit="" IsControllerDefinedType="false" Order="0" OffsetType="">
    <DataType Name="_sHMI_VNC_CLIENT_INFO" BaseType="STRUCT" ArrayType="" Length="" InitialValue="" EnumValue="" Comment="" OffsetChannel="" OffsetBit="" IsControllerDefinedType="true" Order="0" OffsetType="" Id="321e64eb-3bce-4a75-b3b9-a41a228dd5ed">
      <DataType Name="IPAddress" BaseType="String" ArrayType="" Length="" InitialValue="" EnumValue="" Comment="" OffsetChannel="" OffsetBit="" IsControllerDefinedType="true" Order="0" OffsetType="" Id="9fc82e1e-255f-41a1-98a6-9c85a41a8da6" />
      <DataType Name="Comment" BaseType="String" ArrayType="" Length="" InitialValue="" EnumValue="" Comment="" OffsetChannel="" OffsetBit="" IsControllerDefinedType="true" Order="0" OffsetType="" Id="2cb0a830-b20a-449f-8bad-208354d7f921" />
      <DataType Name="MACAddress" BaseType="String" ArrayType="" Length="" InitialValue="" EnumValue="" Comment="" OffsetChannel="" OffsetBit="" IsControllerDefinedType="true" Order="0" OffsetType="" Id="bd846efe-1a6e-4e46-8c25-e3329bdc01c8" />
    </DataType>
    <DataType Name="_eHMI_BUZZER_TYPE" BaseType="ENUM" ArrayType="" Length="" InitialValue="" EnumValue="" Comment="" OffsetChannel="" OffsetBit="" IsControllerDefinedType="true" Order="0" OffsetType="" Id="77b3d809-fcab-4667-ae7c-d475db8b250a">
      <DataType Name="ContinuousBuzzer" BaseType="Integer" ArrayType="" Length="" InitialValue="" EnumValue="0" Comment="" OffsetChannel="" OffsetBit="" IsControllerDefinedType="true" Order="0" OffsetType="" Id="dee0b84a-ca52-48b1-bb5b-253ad4be91a1" />
      <DataType Name="IntermittentShortPulse" BaseType="Integer" ArrayType="" Length="" InitialValue="" EnumValue="1" Comment="" OffsetChannel="" OffsetBit="" IsControllerDefinedType="true" Order="0" OffsetType="" Id="e75550db-91a4-42e8-93e4-d7e24f716f65" />
      <DataType Name="IntermittentLongPulse" BaseType="Integer" ArrayType="" Length="" InitialValue="" EnumValue="2" Comment="" OffsetChannel="" OffsetBit="" IsControllerDefinedType="true" Order="0" OffsetType="" Id="14a895ab-04cd-43cc-9dc0-533d4f67e446" />
    </DataType>
    <DataType Name="_eHMI_SERVICE_STATE" BaseType="ENUM" ArrayType="" Length="" InitialValue="" EnumValue="" Comment="" OffsetChannel="" OffsetBit="" IsControllerDefinedType="true" Order="0" OffsetType="" Id="46bb6427-ec94-4ae4-9fa2-1402b5ade2ff">
      <DataType Name="Running" BaseType="Integer" ArrayType="" Length="" InitialValue="" EnumValue="0" Comment="" OffsetChannel="" OffsetBit="" IsControllerDefinedType="true" Order="0" OffsetType="" Id="247a0ed9-b849-41ff-ba9d-2046e81b4d67" />
      <DataType Name="Suspended" BaseType="Integer" ArrayType="" Length="" InitialValue="" EnumValue="1" Comment="" OffsetChannel="" OffsetBit="" IsControllerDefinedType="true" Order="0" OffsetType="" Id="bfa25910-8e09-420d-853e-d7af62c897c0" />
    </DataType>
    <DataType Name="_eHMI_SERVICE_TYPE" BaseType="ENUM" ArrayType="" Length="" InitialValue="" EnumValue="" Comment="" OffsetChannel="" OffsetBit="" IsControllerDefinedType="true" Order="0" OffsetType="" Id="e367da80-62e6-42fc-8ed1-84828ff916d9">
      <DataType Name="VNCServer" BaseType="Integer" ArrayType="" Length="" InitialValue="" EnumValue="0" Comment="" OffsetChannel="" OffsetBit="" IsControllerDefinedType="true" Order="0" OffsetType="" Id="04376e9a-648d-4857-9e67-4e482f99d6cb" />
    </DataType>
    <DataType Name="_eHMI_KNOWN_PATH" BaseType="ENUM" ArrayType="" Length="" InitialValue="" EnumValue="" Comment="" OffsetChannel="" OffsetBit="" IsControllerDefinedType="true" Order="0" OffsetType="" Id="8428ac2c-8fd8-418a-85cf-4430d38b8920">
      <DataType Name="SDCard" BaseType="Integer" ArrayType="" Length="" InitialValue="" EnumValue="0" Comment="" OffsetChannel="" OffsetBit="" IsControllerDefinedType="true" Order="0" OffsetType="" Id="e82e3d6d-3822-4139-8d43-4856633c3bfa" />
      <DataType Name="USBMemory" BaseType="Integer" ArrayType="" Length="" InitialValue="" EnumValue="1" Comment="" OffsetChannel="" OffsetBit="" IsControllerDefinedType="true" Order="0" OffsetType="" Id="5507677b-9f23-4e12-bb0d-0048158d8e6f" />
    </DataType>
    <DataType Name="_eHMI_TROUBLESHOOTER_PAGE" BaseType="ENUM" ArrayType="" Length="" InitialValue="" EnumValue="" Comment="" OffsetChannel="" OffsetBit="" IsControllerDefinedType="true" Order="0" OffsetType="" Id="e3b19844-b68f-4215-8d58-768c691ad643">
      <DataType Name="ActiveControllerEvents" BaseType="Integer" ArrayType="" Length="" InitialValue="" EnumValue="0" Comment="" OffsetChannel="" OffsetBit="" IsControllerDefinedType="true" Order="0" OffsetType="" Id="06ca072c-8664-4bab-81c9-05eaa7ef698e" />
      <DataType Name="ActiveUserEvents" BaseType="Integer" ArrayType="" Length="" InitialValue="" EnumValue="1" Comment="" OffsetChannel="" OffsetBit="" IsControllerDefinedType="true" Order="0" OffsetType="" Id="6ed031b9-6d89-47ea-a259-fd6fdf159497" />
      <DataType Name="ControllerEventLogs" BaseType="Integer" ArrayType="" Length="" InitialValue="" EnumValue="2" Comment="" OffsetChannel="" OffsetBit="" IsControllerDefinedType="true" Order="0" OffsetType="" Id="8dededfe-ead1-48b3-b4ac-fb9c625a8420" />
      <DataType Name="UserEventLogs" BaseType="Integer" ArrayType="" Length="" InitialValue="" EnumValue="3" Comment="" OffsetChannel="" OffsetBit="" IsControllerDefinedType="true" Order="0" OffsetType="" Id="c9ebaf26-386a-4644-a024-3b6edf8607f5" />
    </DataType>
    <DataType Name="_eHMI_IME_LANGUAGE" BaseType="ENUM" ArrayType="" Length="" InitialValue="" EnumValue="" Comment="" OffsetChannel="" OffsetBit="" IsControllerDefinedType="true" Order="0" OffsetType="" Id="aa12ac08-6254-4d26-bf6e-0a36596fd548">
      <DataType Name="CurrentSystemLanguage" BaseType="Integer" ArrayType="" Length="" InitialValue="" EnumValue="0" Comment="" OffsetChannel="" OffsetBit="" IsControllerDefinedType="true" Order="0" OffsetType="" Id="d8fb0827-6f0a-4f3a-a017-b33ebe85ecef" />
      <DataType Name="Japanese" BaseType="Integer" ArrayType="" Length="" InitialValue="" EnumValue="1" Comment="" OffsetChannel="" OffsetBit="" IsControllerDefinedType="true" Order="0" OffsetType="" Id="c8f966ca-e306-4d56-a7d7-475f6f3ce2d7" />
      <DataType Name="SimplifiedChinese" BaseType="Integer" ArrayType="" Length="" InitialValue="" EnumValue="2" Comment="" OffsetChannel="" OffsetBit="" IsControllerDefinedType="true" Order="0" OffsetType="" Id="d08eee2e-5d8f-4a67-bdce-028b05452d23" />
      <DataType Name="TraditionalChinese" BaseType="Integer" ArrayType="" Length="" InitialValue="" EnumValue="3" Comment="" OffsetChannel="" OffsetBit="" IsControllerDefinedType="true" Order="0" OffsetType="" Id="5201b1f4-75c4-4c3e-a4d8-306a37fbdec8" />
      <DataType Name="Korean" BaseType="Integer" ArrayType="" Length="" InitialValue="" EnumValue="4" Comment="" OffsetChannel="" OffsetBit="" IsControllerDefinedType="true" Order="0" OffsetType="" Id="02eb320f-f5e7-47a4-a80f-a8d084fbc708" />
    </DataType>
    <DataType Name="_eHMI_GRAPH_ZOOM_TARGET" BaseType="ENUM" ArrayType="" Length="" InitialValue="" EnumValue="" Comment="" OffsetChannel="" OffsetBit="" IsControllerDefinedType="true" Order="0" OffsetType="" Id="2190f0f9-eb27-48d1-a9a9-abcac2d82846">
      <DataType Name="Both" BaseType="Integer" ArrayType="" Length="" InitialValue="" EnumValue="0" Comment="" OffsetChannel="" OffsetBit="" IsControllerDefinedType="true" Order="0" OffsetType="" Id="3b3b6d13-7ffe-4a13-b14f-6826328f1f36" />
      <DataType Name="Horizontal" BaseType="Integer" ArrayType="" Length="" InitialValue="" EnumValue="1" Comment="" OffsetChannel="" OffsetBit="" IsControllerDefinedType="true" Order="0" OffsetType="" Id="46ef7ed9-04e9-40cf-b2e8-1acc02e84bcc" />
      <DataType Name="Vertical" BaseType="Integer" ArrayType="" Length="" InitialValue="" EnumValue="2" Comment="" OffsetChannel="" OffsetBit="" IsControllerDefinedType="true" Order="0" OffsetType="" Id="8926a1f3-005a-4143-b931-ad28f8fe3d6e" />
    </DataType>
    <DataType Name="_eHMI_GRAPH_CURSOR" BaseType="ENUM" ArrayType="" Length="" InitialValue="" EnumValue="" Comment="" OffsetChannel="" OffsetBit="" IsControllerDefinedType="true" Order="0" OffsetType="" Id="0c2fe612-4e48-48c8-8cf7-0fa04aacbd7c">
      <DataType Name="Cursor1" BaseType="Integer" ArrayType="" Length="" InitialValue="" EnumValue="1" Comment="" OffsetChannel="" OffsetBit="" IsControllerDefinedType="true" Order="0" OffsetType="" Id="b2c81daa-e1b6-48c4-8388-d15bdfaa0089" />
      <DataType Name="Cursor2" BaseType="Integer" ArrayType="" Length="" InitialValue="" EnumValue="2" Comment="" OffsetChannel="" OffsetBit="" IsControllerDefinedType="true" Order="0" OffsetType="" Id="1595c67c-ed79-4d6b-a3a0-f63b69f45ae2" />
    </DataType>
    <DataType Name="_eHMI_GRAPH_DIRECTION" BaseType="ENUM" ArrayType="" Length="" InitialValue="" EnumValue="" Comment="" OffsetChannel="" OffsetBit="" IsControllerDefinedType="true" Order="0" OffsetType="" Id="507e8c6d-c961-4656-bb3b-e63e5fe50e08">
      <DataType Name="Left" BaseType="Integer" ArrayType="" Length="" InitialValue="" EnumValue="0" Comment="" OffsetChannel="" OffsetBit="" IsControllerDefinedType="true" Order="0" OffsetType="" Id="790204fb-0e9b-47e7-bd5c-94e880eec06e" />
      <DataType Name="Right" BaseType="Integer" ArrayType="" Length="" InitialValue="" EnumValue="1" Comment="" OffsetChannel="" OffsetBit="" IsControllerDefinedType="true" Order="0" OffsetType="" Id="cd348e5a-06a6-470f-96f5-df3bfda0dab6" />
    </DataType>
    <DataType Name="_eHMI_PRIORITY" BaseType="ENUM" ArrayType="" Length="" InitialValue="" EnumValue="" Comment="" OffsetChannel="" OffsetBit="" IsControllerDefinedType="true" Order="0" OffsetType="" Id="c465ebd7-71a6-4b71-a832-f083d24cc5a6">
      <DataType Name="UserFaultLevel1" BaseType="Integer" ArrayType="" Length="" InitialValue="" EnumValue="1" Comment="" OffsetChannel="" OffsetBit="" IsControllerDefinedType="true" Order="0" OffsetType="" Id="0c7bdf60-c03f-4790-8791-d996428506b8" />
      <DataType Name="UserFaultLevel2" BaseType="Integer" ArrayType="" Length="" InitialValue="" EnumValue="2" Comment="" OffsetChannel="" OffsetBit="" IsControllerDefinedType="true" Order="0" OffsetType="" Id="e2c680b6-8eb8-4fb6-b5df-5fb7a7a6bd24" />
      <DataType Name="UserFaultLevel3" BaseType="Integer" ArrayType="" Length="" InitialValue="" EnumValue="4" Comment="" OffsetChannel="" OffsetBit="" IsControllerDefinedType="true" Order="0" OffsetType="" Id="61c8f9e8-7521-4b0b-8b75-b8352763d579" />
      <DataType Name="UserFaultLevel4" BaseType="Integer" ArrayType="" Length="" InitialValue="" EnumValue="8" Comment="" OffsetChannel="" OffsetBit="" IsControllerDefinedType="true" Order="0" OffsetType="" Id="f25a7ddc-d476-47fa-97f0-4d0e5dc84378" />
      <DataType Name="UserFaultLevel5" BaseType="Integer" ArrayType="" Length="" InitialValue="" EnumValue="16" Comment="" OffsetChannel="" OffsetBit="" IsControllerDefinedType="true" Order="0" OffsetType="" Id="52c6bd89-b039-49f5-ba60-09efc841bb88" />
      <DataType Name="UserFaultLevel6" BaseType="Integer" ArrayType="" Length="" InitialValue="" EnumValue="32" Comment="" OffsetChannel="" OffsetBit="" IsControllerDefinedType="true" Order="0" OffsetType="" Id="5fc50634-6529-4552-9417-09bfb2934b46" />
      <DataType Name="UserFaultLevel7" BaseType="Integer" ArrayType="" Length="" InitialValue="" EnumValue="64" Comment="" OffsetChannel="" OffsetBit="" IsControllerDefinedType="true" Order="0" OffsetType="" Id="b52481eb-e6fb-4029-a497-c4ab559677b5" />
      <DataType Name="UserFaultLevel8" BaseType="Integer" ArrayType="" Length="" InitialValue="" EnumValue="128" Comment="" OffsetChannel="" OffsetBit="" IsControllerDefinedType="true" Order="0" OffsetType="" Id="6c8a75ac-f9ab-4fcf-8939-48fb03157ca9" />
      <DataType Name="UserInformation" BaseType="Integer" ArrayType="" Length="" InitialValue="" EnumValue="256" Comment="" OffsetChannel="" OffsetBit="" IsControllerDefinedType="true" Order="0" OffsetType="" Id="8edc8652-76fe-4896-84d0-56782a4fcb36" />
      <DataType Name="All" BaseType="Integer" ArrayType="" Length="" InitialValue="" EnumValue="511" Comment="" OffsetChannel="" OffsetBit="" IsControllerDefinedType="true" Order="0" OffsetType="" Id="3f69d056-b204-4c4d-861c-2736f8eeb26f" />
    </DataType>
    <DataType Name="_eHMI_COLUMN" BaseType="ENUM" ArrayType="" Length="" InitialValue="" EnumValue="" Comment="" OffsetChannel="" OffsetBit="" IsControllerDefinedType="true" Order="0" OffsetType="" Id="65e2d3cb-5176-4d1b-ab7a-903502dfb79f">
      <DataType Name="DateAndTime" BaseType="Integer" ArrayType="" Length="" InitialValue="" EnumValue="1" Comment="" OffsetChannel="" OffsetBit="" IsControllerDefinedType="true" Order="0" OffsetType="" Id="25b83b45-e1fb-4cd2-889e-a494caddbf14" />
      <DataType Name="Message" BaseType="Integer" ArrayType="" Length="" InitialValue="" EnumValue="2" Comment="" OffsetChannel="" OffsetBit="" IsControllerDefinedType="true" Order="0" OffsetType="" Id="fbd3fce7-98cc-49b2-965d-c5ddb0289101" />
      <DataType Name="Priority" BaseType="Integer" ArrayType="" Length="" InitialValue="" EnumValue="4" Comment="" OffsetChannel="" OffsetBit="" IsControllerDefinedType="true" Order="0" OffsetType="" Id="73f4ac3f-0ab1-473f-9518-ac0cbc1c035a" />
      <DataType Name="Group" BaseType="Integer" ArrayType="" Length="" InitialValue="" EnumValue="8" Comment="" OffsetChannel="" OffsetBit="" IsControllerDefinedType="true" Order="0" OffsetType="" Id="247634e5-1fe3-4dae-a1f7-61be6995940e" />
      <DataType Name="AlarmCode" BaseType="Integer" ArrayType="" Length="" InitialValue="" EnumValue="16" Comment="" OffsetChannel="" OffsetBit="" IsControllerDefinedType="true" Order="0" OffsetType="" Id="f9e18858-3a6d-45b6-9fb7-589a60cbb36f" />
      <DataType Name="Name" BaseType="Integer" ArrayType="" Length="" InitialValue="" EnumValue="32" Comment="" OffsetChannel="" OffsetBit="" IsControllerDefinedType="true" Order="0" OffsetType="" Id="b3e8bfad-4e09-446f-aec0-31662fce4672" />
      <DataType Name="LoggedInUser" BaseType="Integer" ArrayType="" Length="" InitialValue="" EnumValue="64" Comment="" OffsetChannel="" OffsetBit="" IsControllerDefinedType="true" Order="0" OffsetType="" Id="a74ac2ec-45fe-49ad-bb4c-174dfbf7b818" />
      <DataType Name="Status" BaseType="Integer" ArrayType="" Length="" InitialValue="" EnumValue="128" Comment="" OffsetChannel="" OffsetBit="" IsControllerDefinedType="true" Order="0" OffsetType="" Id="377a44f4-4113-4148-a515-a0c6ff9adae0" />
      <DataType Name="All" BaseType="Integer" ArrayType="" Length="" InitialValue="" EnumValue="255" Comment="" OffsetChannel="" OffsetBit="" IsControllerDefinedType="true" Order="0" OffsetType="" Id="da80ee69-7926-470b-90c4-7f148927f5b1" />
    </DataType>
    <DataType Name="_eHMI_ALARM_STATUS" BaseType="ENUM" ArrayType="" Length="" InitialValue="" EnumValue="" Comment="" OffsetChannel="" OffsetBit="" IsControllerDefinedType="true" Order="0" OffsetType="" Id="9d1315f1-dce3-4e9d-93bd-37a6096bfe56">
      <DataType Name="RaisedUnacknowledged" BaseType="Integer" ArrayType="" Length="" InitialValue="" EnumValue="1" Comment="" OffsetChannel="" OffsetBit="" IsControllerDefinedType="true" Order="0" OffsetType="" Id="0988d8fb-5154-40a4-9974-3c66c4655b53" />
      <DataType Name="RaisedAckNotRequired" BaseType="Integer" ArrayType="" Length="" InitialValue="" EnumValue="2" Comment="" OffsetChannel="" OffsetBit="" IsControllerDefinedType="true" Order="0" OffsetType="" Id="93c1db48-d6fb-4577-9762-6c98c9283166" />
      <DataType Name="RaisedAcknowledged" BaseType="Integer" ArrayType="" Length="" InitialValue="" EnumValue="4" Comment="" OffsetChannel="" OffsetBit="" IsControllerDefinedType="true" Order="0" OffsetType="" Id="03a27c00-ed99-4262-939b-14ea7f013d47" />
      <DataType Name="ClearedUnacknowledged" BaseType="Integer" ArrayType="" Length="" InitialValue="" EnumValue="8" Comment="" OffsetChannel="" OffsetBit="" IsControllerDefinedType="true" Order="0" OffsetType="" Id="037a94f3-ff93-4b7b-9c20-3d95a096e18c" />
      <DataType Name="ClearedAckNotRequired" BaseType="Integer" ArrayType="" Length="" InitialValue="" EnumValue="16" Comment="" OffsetChannel="" OffsetBit="" IsControllerDefinedType="true" Order="0" OffsetType="" Id="80656295-de98-4e48-b62e-9a95caf92f3f" />
      <DataType Name="ClearedAcknowledged" BaseType="Integer" ArrayType="" Length="" InitialValue="" EnumValue="32" Comment="" OffsetChannel="" OffsetBit="" IsControllerDefinedType="true" Order="0" OffsetType="" Id="77152ed9-850b-4712-96b9-3c906709c974" />
      <DataType Name="All" BaseType="Integer" ArrayType="" Length="" InitialValue="" EnumValue="63" Comment="" OffsetChannel="" OffsetBit="" IsControllerDefinedType="true" Order="0" OffsetType="" Id="6bf37f1d-93bf-4aec-8df6-eb971da7c0bb" />
      <DataType Name="Raised" BaseType="Integer" ArrayType="" Length="" InitialValue="" EnumValue="7" Comment="" OffsetChannel="" OffsetBit="" IsControllerDefinedType="true" Order="0" OffsetType="" Id="204a51c5-de31-4411-b8a7-0b25e010d348" />
      <DataType Name="Cleared" BaseType="Integer" ArrayType="" Length="" InitialValue="" EnumValue="56" Comment="" OffsetChannel="" OffsetBit="" IsControllerDefinedType="true" Order="0" OffsetType="" Id="52115cdf-4fce-4039-99fe-827bf9feb0d9" />
      <DataType Name="Acknowledged" BaseType="Integer" ArrayType="" Length="" InitialValue="" EnumValue="36" Comment="" OffsetChannel="" OffsetBit="" IsControllerDefinedType="true" Order="0" OffsetType="" Id="52a5c507-9660-4888-b4b0-b6340ea9fddb" />
      <DataType Name="Unacknowledged" BaseType="Integer" ArrayType="" Length="" InitialValue="" EnumValue="9" Comment="" OffsetChannel="" OffsetBit="" IsControllerDefinedType="true" Order="0" OffsetType="" Id="a068d389-77ee-490d-9ba7-666fc2d6e2ea" />
    </DataType>
    <DataType Name="_eHMI_SORT_ORDER" BaseType="ENUM" ArrayType="" Length="" InitialValue="" EnumValue="" Comment="" OffsetChannel="" OffsetBit="" IsControllerDefinedType="true" Order="0" OffsetType="" Id="4081af29-00ba-45ae-8650-c9e62203c80c">
      <DataType Name="Ascending" BaseType="Integer" ArrayType="" Length="" InitialValue="" EnumValue="0" Comment="" OffsetChannel="" OffsetBit="" IsControllerDefinedType="true" Order="0" OffsetType="" Id="6a1f17ea-1b8b-4290-8398-47d96fb7c0ed" />
      <DataType Name="Descending" BaseType="Integer" ArrayType="" Length="" InitialValue="" EnumValue="1" Comment="" OffsetChannel="" OffsetBit="" IsControllerDefinedType="true" Order="0" OffsetType="" Id="dff3dcdf-ced0-4aef-a863-f0da4df6dd0f" />
    </DataType>
  </DataType>
</data>